{
  "particles": {
    "number": {
      "value": 55,
      "density": {
        "enable": true,
        "value_are": 200
      }
    },
    "color": {
      "value": "random"
    },
    "shape": {
      "type": ["circle", "star", "edge"]
    },
    "opacity": {
      "value": 0.55,
      "anim": {
        "enable": true,
        "speed": 2,
        "opacity_min": 0.25,
        "sync": true
      }
    },
    "size": {
      "value": 5,
      "random": true,
      "anim": {
        "enable": true,
        "speed": 10,
        "size_min": 7,
        "sync": true
      }
    },
    "line_linked": {
      "enable": true,
      "distance": 100,
      "color": "#000000",
      "opacity": 1.75,
      "width": 0.35
    },
    "move": {
      "enable": true,
      "speed": 1.75,
      "direction": "none",
      "random": true,
      "straight": false,
      "out-mode": "bounce",
      "bounce": true,
      "attract": {
        "enable": true,
        "rotateX": 1000,
        "rotateY": 1200
      }
    }
  },
  "interactivity": {
    "detect_on": "canvas",
    "events": {
      "onhover": {
        "enable": true,
        "mode": "grab"
      },
      "onclick": {
        "enable": true,
        "mode": "bubble"
      },
      "resize": true
    },
    "modes": {
      "grab": {
        "distance": 200,
        "line_linked": {
          "opacity": 0.95
        }
      },
      "bubble": {
        "distance": 300,
        "size": 7.95,
        "duration": 0.15,
        "opacity": 0.75,
        "speed": 1.75
      }
    }
  },
  "retina_detect": true
}
